LICENSE
divo/__init__.py
divo/bluetooth_base.py
divo/bluetooth_serial.py
divo/bluetooth_socket.py
divo/command.py
divo/command_base.py
divo/evo_encoder.py
divo/evo_pixmap.py
divo/exceptions.py
divo/helpers.py
divo/image.py
divo/main.py
divo/packet.py
divo/packet_base.py
divo/packet_stream.py
divo/pixoo.py
divo/test.png
divo/test.py
divo-0.1.0.dist-info/entry_points.txt
divo-0.1.0.dist-info/LICENSE
divo-0.1.0.dist-info/WHEEL
divo-0.1.0.dist-info/METADATA
divo-0.1.0.dist-info/RECORD
