Metadata-Version: 2.1
Name: divo
Version: 0.1.0
Summary: 
Home-page: https://github.com/spezifisch/divo
License: GPL-3.0-only
Keywords: divoom,pixoo,timebox,evo
Author: spezifisch
Author-email: spezifisch-gpl.7e6@below.fr
Requires-Python: >=3.7,<4.0
Classifier: Development Status :: 3 - Alpha
Classifier: Environment :: Console
Classifier: License :: OSI Approved :: GNU General Public License v3 (GPLv3)
Classifier: Operating System :: OS Independent
Classifier: Programming Language :: Python :: 3
Classifier: Programming Language :: Python :: 3.10
Classifier: Programming Language :: Python :: 3.7
Classifier: Programming Language :: Python :: 3.8
Classifier: Programming Language :: Python :: 3.9
Requires-Dist: Pillow (>=9.0.0,<10.0.0)
Requires-Dist: click (>=8.0.3,<9.0.0)
Requires-Dist: colorconsole (>=0.7.2,<0.8.0)
Requires-Dist: loguru (>=0.5.3,<0.6.0)
Requires-Dist: pyserial (>=3.5,<4.0)
Project-URL: Repository, https://github.com/spezifisch/divo
